{
  "title": "Почему мы?",
  "cols": [
    {
      "items": [
        {
          "item": "Опыт выполнения масштабных проектов, разработки и реализации стратегий импортозамещения"
        },
        {
          "item": "Собственная лаборатория для прототипирования решений"
        },
        {
          "item": "Штат высококвалифицированных инженеров и архитекторов"
        },
        {
          "item": "Сертифицированные специалисты по ведущим российским решениям и продуктам"
        }
      ]
    },
    {
      "items": [
        {
          "item": "Поставка оборудования и лицензий ведущих производителей быстро и выгодно"
        },
        {
          "item": "Кросс-функциональная экспертиза, привлечение специалистов из смежных центров компетенций"
        },
        {
          "item": "Финансово-устойчивый надёжный партнёр"
        }
      ]
    }
  ]
}